odoo/addons/pos_pricelist_technical/README.rst
odoo/addons/pos_pricelist_technical/__init__.py
odoo/addons/pos_pricelist_technical/__manifest__.py
odoo/addons/pos_pricelist_technical/i18n/fr.po
odoo/addons/pos_pricelist_technical/i18n/it.po
odoo/addons/pos_pricelist_technical/i18n/pos_pricelist_technical.pot
odoo/addons/pos_pricelist_technical/models/__init__.py
odoo/addons/pos_pricelist_technical/models/pos_order.py
odoo/addons/pos_pricelist_technical/readme/CONTRIBUTORS.rst
odoo/addons/pos_pricelist_technical/readme/DESCRIPTION.rst
odoo/addons/pos_pricelist_technical/readme/ROADMAP.rst
odoo/addons/pos_pricelist_technical/readme/USAGE.rst
odoo/addons/pos_pricelist_technical/static/description/icon.png
odoo/addons/pos_pricelist_technical/static/description/index.html
odoo/addons/pos_pricelist_technical/static/description/pos_config_form.png
odoo/addons/pos_pricelist_technical/static/description/pos_front_end_ui.png
odoo/addons/pos_pricelist_technical/static/src/js/models.js
odoo/addons/pos_pricelist_technical/static/src/js/screens.js
odoo/addons/pos_pricelist_technical/static/src/xml/pos_pricelist_technical.xml
odoo/addons/pos_pricelist_technical/views/templates.xml
odoo12_addon_pos_pricelist_technical-12.0.1.0.1.99.dev12.dist-info/METADATA
odoo12_addon_pos_pricelist_technical-12.0.1.0.1.99.dev12.dist-info/WHEEL
odoo12_addon_pos_pricelist_technical-12.0.1.0.1.99.dev12.dist-info/top_level.txt
odoo12_addon_pos_pricelist_technical-12.0.1.0.1.99.dev12.dist-info/RECORD
