Metadata-Version: 2.1
Name: odoo12-addon-pos-pricelist-technical
Version: 12.0.1.0.1.99.dev12
Summary: Prevent technical pricelists from being displayed in the Point of Sale front-end UI
Home-page: https://github.com/OCA/pos
Author: GRAP,Odoo Community Association (OCA)
Author-email: support@odoo-community.org
License: AGPL-3
Platform: UNKNOWN
Classifier: Programming Language :: Python
Classifier: Framework :: Odoo
Classifier: Framework :: Odoo :: 12.0
Classifier: License :: OSI Approved :: GNU Affero General Public License v3
Requires-Python: >=3.5
Requires-Dist: odoo12-addon-sale-pricelist-technical
Requires-Dist: odoo <12.1dev,>=12.0a
